.syncshell.ini
README.md
pyproject.toml
syncshell/__init__.py
syncshell/cli.py
syncshell/utils/__init__.py
syncshell/utils/config.py
syncshell/utils/constants.py
syncshell/utils/spinner.py
syncshell-1.1.0.dist-info/METADATA
syncshell-1.1.0.dist-info/WHEEL
syncshell-1.1.0.dist-info/entry_points.txt
syncshell-1.1.0.dist-info/licenses/LICENSE
syncshell-1.1.0.dist-info/RECORD
