Metadata-Version: 2.4
Name: syncshell
Version: 1.1.0
Summary: Keep your machine's shell history synchronized
License: MIT
License-File: LICENSE
Keywords: sync,shell,history,bash,zsh
Author: Masoud Ghorbani
Author-email: masoudghorbani@pm.me
Requires-Python: >=3.12,<4.0
Classifier: Development Status :: 5 - Production/Stable
Classifier: Intended Audience :: Developers
Classifier: License :: OSI Approved :: MIT License
Classifier: Natural Language :: English
Classifier: Programming Language :: Python :: 3
Classifier: Programming Language :: Python :: 3.12
Classifier: Programming Language :: Python :: 3.13
Classifier: Programming Language :: Python :: 3.14
Classifier: Programming Language :: Python :: 3.15
Classifier: Topic :: Software Development
Classifier: Topic :: System :: Shells
Classifier: Topic :: Utilities
Requires-Dist: PyGithub (==2.8.1)
Requires-Dist: fire (==0.7.1)
Requires-Dist: halo (==0.0.31)
Project-URL: Homepage, https://github.com/masoudgs/syncshell
Project-URL: Repository, https://github.com/masoudgs/syncshell
